pyrus.py
pyrus-1.1.1.dist-info/DESCRIPTION.rst
pyrus-1.1.1.dist-info/METADATA
pyrus-1.1.1.dist-info/RECORD
pyrus-1.1.1.dist-info/WHEEL
pyrus-1.1.1.dist-info/metadata.json
pyrus-1.1.1.dist-info/pbr.json
pyrus-1.1.1.dist-info/top_level.txt
